README.rst
setup.py
maestro_cli/__init__.py
maestro_cli/api.py
maestro_cli/config.py
maestro_cli/jobrequest.py
maestro_cli/maestro.py
maestro_cli/utils.py
maestro_cli.egg-info/PKG-INFO
maestro_cli.egg-info/SOURCES.txt
maestro_cli.egg-info/dependency_links.txt
maestro_cli.egg-info/not-zip-safe
maestro_cli.egg-info/requires.txt
maestro_cli.egg-info/top_level.txt