Metadata-Version: 1.1
Name: maestro-cli
Version: 1.0.10
Summary: Launch and monitor Maestro JobRequest in few lines of code.
Home-page: https://bitbucket.org/monalgroup/maestro-cli/
Author: Fantomas42
Author-email: julien.fache@hiventy.com
License: BSD License
Keywords: maestro,jobrequest
Platform: any
Classifier: Intended Audience :: Developers
Classifier: Programming Language :: Python :: 2.7
Classifier: License :: OSI Approved :: BSD License
Classifier: Topic :: Software Development :: Build Tools
Classifier: Topic :: Software Development :: Libraries :: Python Modules
